README.rst
setup.py
zlsys/__init__.py
zlsys/db_task.py
zlsys/download.py
zlsys/src.py
zlsys/t_gg.py
zlsys/tohawq.py
zlsys/zlsys_guangdongsheng_shenzhenshi.py
zlsys/zlsys_sichuan_suiningshi.py
zlsys/zlsys_sichuan_yaanshi.py
zlsys/zlsys_sichuan_yibinshi.py
zlsys/zlsys_yunnan_baoshanshi.py
zlsys/zlsys_yunnan_chuxiongzhou.py
zlsys/zlsys_yunnan_dalizhou.py
zlsys/zlsys_yunnan_dehongzhou.py
zlsys/zlsys_yunnan_diqingzhou.py
zlsys/zlsys_yunnan_honghezhou.py
zlsys/zlsys_yunnan_kunmingshi.py
zlsys/zlsys_yunnan_lijiangshi.py
zlsys/zlsys_yunnan_lincangshi.py
zlsys/zlsys_yunnan_nujiangzhou.py
zlsys/zlsys_yunnan_puershi.py
zlsys/zlsys_yunnan_qujingshi.py
zlsys/zlsys_yunnan_tengchongshi.py
zlsys/zlsys_yunnan_wenshanzhou.py
zlsys/zlsys_yunnan_xishuangbanna.py
zlsys/zlsys_yunnan_yunnansheng.py
zlsys/zlsys_yunnan_yuxishi.py
zlsys/zlsys_yunnan_zhaotongshi.py
zlsys.egg-info/PKG-INFO
zlsys.egg-info/SOURCES.txt
zlsys.egg-info/dependency_links.txt
zlsys.egg-info/requires.txt
zlsys.egg-info/top_level.txt